spaceship/__init__.py
spaceship/game.py
spaceship/demo/demo.py
spaceship/input/__init__.py
spaceship/input/input.py
spaceship/render/__init__.py
spaceship/render/camera.py
spaceship/render/entity.py
spaceship/render/hud.py
spaceship/render/render.py
spaceship/render/sprite.py
spaceship/utils/__init__.py
spaceship/utils/constants.py
spaceship/utils/math.py
spaceship_engine-0.1.4.dist-info/licenses/LICENSE
spaceship_engine-0.1.4.dist-info/METADATA
spaceship_engine-0.1.4.dist-info/WHEEL
spaceship_engine-0.1.4.dist-info/top_level.txt
spaceship_engine-0.1.4.dist-info/RECORD
