Metadata-Version: 2.4
Name: spaceship-engine
Version: 0.1.4
Summary: A game engine for building games for CLIs
Author-email: falingunit <sbaniruddh1@gmail.com>
License-Expression: MIT
Project-URL: Homepage, https://github.com/Falingunit/spaceship
Requires-Python: >=3.8
License-File: LICENSE
Requires-Dist: pynput
Dynamic: license-file
